{
    "cosmic": {
        "spriteID": 64,
        "monkeyID": "monkey_cosmic"
    },
    "basic": {
        "spriteID": 0,
        "monkeyID": "monkey_basic"
    },
    "green": {
        "spriteID": 1,
        "monkeyID": "monkey_green"
    },
    "blue": {
        "spriteID": 2,
        "monkeyID": "monkey_blue"
    },
    "yellow": {
        "spriteID": 3,
        "monkeyID": "monkey_yellow"
    },
    "red": {
        "spriteID": 4,
        "monkeyID": "monkey_red"
    },
    "orange": {
        "spriteID": 5,
        "monkeyID": "monkey_orange"
    },
    "purple": {
        "spriteID": 6,
        "monkeyID": "monkey_purple"
    },
    "old": {
        "spriteID": 7,
        "monkeyID": "monkey_old"
    },
    "wise": {
        "spriteID": 8,
        "monkeyID": "monkey_wise"
    },
    "smart": {
        "spriteID": 9,
        "monkeyID": "monkey_smart"
    },
    "wizard": {
        "spriteID": 10,
        "monkeyID": "monkey_wizard"
    },
    "devil": {
        "spriteID": 11,
        "monkeyID": "monkey_devil"
    },
    "angel": {
        "spriteID": 12,
        "monkeyID": "monkey_angel"
    },
    "yeti": {
        "spriteID": 13,
        "monkeyID": "monkey_yeti"
    },
    "slime": {
        "spriteID": 14,
        "monkeyID": "monkey_slime"
    },
    "water": {
        "spriteID": 15,
        "monkeyID": "monkey_water"
    },
    "ice": {
        "spriteID": 16,
        "monkeyID": "monkey_ice"
    },
    "earth": {
        "spriteID": 17,
        "monkeyID": "monkey_earth"
    },
    "fire": {
        "spriteID": 18,
        "monkeyID": "monkey_fire"
    },
    "lightning": {
        "spriteID": 19,
        "monkeyID": "monkey_lightning"
    },
    "golden": {
        "spriteID": 20,
        "monkeyID": "monkey_golden"
    },
    "void": {
        "spriteID": 21,
        "monkeyID": "monkey_void"
    },
    "shadow": {
        "spriteID": 22,
        "monkeyID": "monkey_shadow"
    },
    "leaf": {
        "spriteID": 23,
        "monkeyID": "monkey_leaf"
    },
    "jaded": {
        "spriteID": 24,
        "monkeyID": "monkey_jaded"
    },
    "poison": {
        "spriteID": 25,
        "monkeyID": "monkey_poison"
    },
    "crystal": {
        "spriteID": 26,
        "monkeyID": "monkey_crystal"
    },
    "ghost": {
        "spriteID": 27,
        "monkeyID": "monkey_ghost"
    },
    "bubble": {
        "spriteID": 28,
        "monkeyID": "monkey_bubble"
    },
    "plasma": {
        "spriteID": 29,
        "monkeyID": "monkey_plasma"
    },
    "mango": {
        "spriteID": 30,
        "monkeyID": "monkey_mango"
    },
    "rainbow": {
        "spriteID": 31,
        "monkeyID": "monkey_rainbow"
    },
    "egg": {
        "spriteID": 32,
        "monkeyID": "monkey_egg"
    },
    "monocle": {
        "spriteID": 33,
        "monkeyID": "monkey_monocle"
    },
    "thoughtless": {
        "spriteID": 34,
        "monkeyID": "monkey_thoughtless"
    },
    "allSeer": {
        "spriteID": 35,
        "monkeyID": "monkey_allseer"
    }
}
